README.rst
setup.cfg
setup.py
existpy/__init__.py
existpy/cli.py
existpy/command.py
existpy.egg-info/PKG-INFO
existpy.egg-info/SOURCES.txt
existpy.egg-info/dependency_links.txt
existpy.egg-info/entry_points.txt
existpy.egg-info/requires.txt
existpy.egg-info/top_level.txt
existpy.egg-info/zip-safe