Metadata-Version: 1.1
Name: existpy
Version: 0.0.1
Summary: CLI tool for checking if a given project name exists in `pipy`.
Home-page: https://github.com/existpy
Author: Monika Ilieva
Author-email: hidden@hidden.com
License: MIT License
Keywords: existpy package pypi python
Platform: UNKNOWN
Classifier: Environment :: Console
Classifier: Intended Audience :: Developers
Classifier: License :: OSI Approved :: MIT License
